lore_explainer/__init__.py
lore_explainer/datamanager.py
lore_explainer/decision_tree.py
lore_explainer/explanation.py
lore_explainer/lorem.py
lore_explainer/neighgen.py
lore_explainer/rule.py
lore_explainer/util.py
LORE_ext-1.0.3.dist-info/LICENSE.txt
LORE_ext-1.0.3.dist-info/METADATA
LORE_ext-1.0.3.dist-info/WHEEL
LORE_ext-1.0.3.dist-info/top_level.txt
LORE_ext-1.0.3.dist-info/RECORD
