Metadata-Version: 2.1
Name: LORE_ext
Version: 1.0.3
Summary: LORE (LOcal Rule-based Explanations) is a model-agnostic explanator for tabular data
Home-page: https://www.ai4europe.eu/research/ai-catalog/lore
Author: rinziv
Author-email: rinzivillo@isti.cnr.it
License: MIT
Project-URL: Documentation, http://lore-ext.readthedocs.io/
Project-URL: Source, https://github.com/rinziv/LORE_Ext
Platform: any
Classifier: Development Status :: 4 - Beta
Classifier: Programming Language :: Python
License-File: LICENSE.txt
Requires-Dist: numpy
Requires-Dist: pandas
Requires-Dist: deap
Requires-Dist: pillow
Requires-Dist: scipy
Requires-Dist: scikit-learn
Requires-Dist: bitarray
Requires-Dist: importlib-metadata ; python_version < "3.8"
Provides-Extra: testing
Requires-Dist: setuptools ; extra == 'testing'
Requires-Dist: pytest ; extra == 'testing'
Requires-Dist: pytest-cov ; extra == 'testing'
